[{"paths":["face_recognition_model-shard1.weights","face_recognition_model-shard2.weights"],"weights":[{"name":"conv_1/filters","shape":[3,3,3,32],"dtype":"float32"},{"name":"conv_1/biases","shape":[32],"dtype":"float32"},{"name":"conv_2/filters","shape":[3,3,32,64],"dtype":"float32"},{"name":"conv_2/biases","shape":[64],"dtype":"float32"},{"name":"conv_3/filters","shape":[3,3,64,64],"dtype":"float32"},{"name":"conv_3/biases","shape":[64],"dtype":"float32"},{"name":"conv_4/filters","shape":[3,3,64,128],"dtype":"float32"},{"name":"conv_4/biases","shape":[128],"dtype":"float32"},{"name":"conv_5/filters","shape":[3,3,128,128],"dtype":"float32"},{"name":"conv_5/biases","shape":[128],"dtype":"float32"},{"name":"conv_6/filters","shape":[3,3,128,256],"dtype":"float32"},{"name":"conv_6/biases","shape":[256],"dtype":"float32"},{"name":"conv_7/filters","shape":[3,3,256,256],"dtype":"float32"},{"name":"conv_7/biases","shape":[256],"dtype":"float32"},{"name":"conv_8/filters","shape":[3,3,256,512],"dtype":"float32"},{"name":"conv_8/biases","shape":[512],"dtype":"float32"},{"name":"conv_9/filters","shape":[3,3,512,512],"dtype":"float32"},{"name":"conv_9/biases","shape":[512],"dtype":"float32"},{"name":"fc_1/weights","shape":[25088,512],"dtype":"float32"},{"name":"fc_1/biases","shape":[512],"dtype":"float32"},{"name":"fc_2/weights","shape":[512,128],"dtype":"float32"}]}]